passwordstrength/dir.py
passwordstrength/entropy.py
passwordstrength/passwordmeter.py
passwordstrength/util.py
passwordstrength/database/google-10000-english.txt
passwordstrength/database/leetspeak.yaml
passwordstrength/database/words.txt
passwordstrength-0.2.4.dist-info/METADATA
passwordstrength-0.2.4.dist-info/RECORD
passwordstrength-0.2.4.dist-info/WHEEL
passwordstrength-0.2.4.dist-info/top_level.txt
