Metadata-Version: 2.1
Name: passwordstrength
Version: 0.2.4
Summary: Password strength calculator in Python
Home-page: https://github.com/patarapolw/passwordstrength
Author: Pacharapol Withayasakpunt
Author-email: patarapolw@gmail.com
License: MIT
Keywords: password password_strength password_meter
Platform: UNKNOWN
Classifier: Development Status :: 4 - Beta
Classifier: Environment :: Console
Classifier: Intended Audience :: Developers
Classifier: Intended Audience :: Information Technology
Classifier: License :: OSI Approved :: MIT License
Classifier: Operating System :: OS Independent
Classifier: Programming Language :: Python :: 3.5
Classifier: Programming Language :: Python :: 3.6
Classifier: Topic :: Security :: Cryptography
Requires-Python: >=3.5
Provides-Extra: analysis
Provides-Extra: tests
